csv_fix/__init__.py
csv_fix/__main__.py
csv_fix/csv_state_machine.py
csv_fix/states.py
csv_fix-0.3.0.dist-info/licenses/LICENSE
csv_fix-0.3.0.dist-info/METADATA
csv_fix-0.3.0.dist-info/WHEEL
csv_fix-0.3.0.dist-info/entry_points.txt
csv_fix-0.3.0.dist-info/top_level.txt
csv_fix-0.3.0.dist-info/RECORD
